signalwave/__init__.py
signalwave/core.py
signalwave/utils.py
signalwave-1.0.dist-info/METADATA
signalwave-1.0.dist-info/WHEEL
signalwave-1.0.dist-info/top_level.txt
signalwave-1.0.dist-info/RECORD
