Metadata-Version: 2.2
Name: signalwave
Version: 1.0
Summary: A library for creating and analyzing signal wave function models.
Home-page: https://sourceduty.com
Author: Sourceduty
Author-email: sourceduty@gmail.com
Classifier: Programming Language :: Python :: 3
Classifier: License :: OSI Approved :: MIT License
Classifier: Operating System :: OS Independent
Requires-Python: >=3.6
Requires-Dist: numpy
Dynamic: author
Dynamic: author-email
Dynamic: classifier
Dynamic: description
Dynamic: description-content-type
Dynamic: home-page
Dynamic: requires-dist
Dynamic: requires-python
Dynamic: summary
